MANIFEST.in
README.rst
setup.cfg
setup.py
pywebify/__init__.py
pywebify/config.ini
pywebify/pywebify.py
pywebify/setup.txt
pywebify/template.py
pywebify/version.txt
pywebify/webpage.py
pywebify.egg-info/PKG-INFO
pywebify.egg-info/SOURCES.txt
pywebify.egg-info/dependency_links.txt
pywebify.egg-info/requires.txt
pywebify.egg-info/top_level.txt
pywebify/img/collapsed.png
pywebify/img/expanded.png
pywebify/img/favicon.png
pywebify/js/collapse.js
pywebify/js/div_switch.js
pywebify/js/div_toggle.js
pywebify/js/filter.js
pywebify/js/pixelate.js
pywebify/templates/css/collapse.css
pywebify/templates/css/filter.css
pywebify/templates/css/pixelate.css
pywebify/templates/css/rst.css
pywebify/templates/css/webify.css
pywebify/templates/html/navbar.html
pywebify/templates/html/webify.html
pywebify/templates/jinja/tabs.html
pywebify/templates/jinja/webpage.html