Metadata-Version: 1.1
Name: pywebify
Version: 0.2.6
Summary: Browser-based html/image file report builder
Home-page: https://github.com/endangeredoxen/pywebify
Author: Steve Nicholes
Author-email: endangeredoxen@users.noreply.github.com
License: GPLv3
Download-URL: https://github.com/endangeredoxen/pywebify/archive/v0.2.6.tar.gz
Keywords: data,web report
Platform: UNKNOWN
